[
  {
    "name": "Summon Storm Cubic",
    "id": 10,
    "levels": 8,
    "power": [
      282,
      434,
      677,
      919,
      1141,
      1394,
      1673,
      1975
    ],
    "mpCost": [
      28,
      33,
      38,
      43,
      46,
      49,
      52,
      55
    ],
    "magicLevel": [
      40,
      46,
      52,
      58,
      62,
      66,
      70,
      74
    ],
    "duration": null,
    "skillType": "summon",
    "operateType": "active",
    "target": "self",
    "isMagic": true,
    "ignoreShld": false,
    "weaponsAllowed": [],
    "element": "none",
    "elementPower": 0,
    "levelDepend": 0,
    "ignoreResists": false,
    "canBeReflected": true,
    "effects": []
  },
  {
    "name": "Summon Siege Golem",
    "id": 13,
    "levels": 1,
    "power": [],
    "mpCost": [],
    "magicLevel": [],
    "duration": null,
    "skillType": "summon",
    "operateType": "active",
    "target": "self",
    "isMagic": false,
    "ignoreShld": false,
    "weaponsAllowed": [],
    "element": "none",
    "elementPower": 0,
    "levelDepend": 0,
    "ignoreResists": false,
    "canBeReflected": true,
    "effects": []
  },
  {
    "name": "Summon Vampiric Cubic",
    "id": 22,
    "levels": 7,
    "power": [
      351,
      531,
      773,
      1026,
      1264,
      1530,
      1822
    ],
    "mpCost": [
      30,
      35,
      40,
      44,
      48,
      51,
      53
    ],
    "magicLevel": [
      43,
      49,
      55,
      60,
      64,
      68,
      72
    ],
    "duration": null,
    "skillType": "summon",
    "operateType": "active",
    "target": "self",
    "isMagic": true,
    "ignoreShld": false,
    "weaponsAllowed": [],
    "element": "none",
    "elementPower": 0,
    "levelDepend": 0,
    "ignoreResists": false,
    "canBeReflected": true,
    "effects": []
  },
  {
    "name": "Summon Mechanic Golem",
    "id": 25,
    "levels": 9,
    "power": [],
    "mpCost": [
      49,
      62,
      75,
      88,
      100,
      110,
      119,
      126,
      133
    ],
    "magicLevel": [],
    "duration": null,
    "skillType": "summon",
    "operateType": "active",
    "target": "self",
    "isMagic": false,
    "ignoreShld": false,
    "weaponsAllowed": [],
    "element": "none",
    "elementPower": 0,
    "levelDepend": 0,
    "ignoreResists": false,
    "canBeReflected": true,
    "effects": []
  },
  {
    "name": "Summon Phantom Cubic",
    "id": 33,
    "levels": 8,
    "power": [
      282,
      434,
      644,
      919,
      1141,
      1394,
      1673,
      1975
    ],
    "mpCost": [
      28,
      33,
      38,
      43,
      46,
      49,
      52,
      55
    ],
    "magicLevel": [
      40,
      46,
      52,
      58,
      62,
      66,
      70,
      74
    ],
    "duration": null,
    "skillType": "summon",
    "operateType": "active",
    "target": "self",
    "isMagic": true,
    "ignoreShld": false,
    "weaponsAllowed": [],
    "element": "none",
    "elementPower": 0,
    "levelDepend": 0,
    "ignoreResists": false,
    "canBeReflected": true,
    "effects": []
  },
  {
    "name": "Summon Life Cubic",
    "id": 67,
    "levels": 7,
    "power": [],
    "mpCost": [
      30,
      35,
      40,
      44,
      48,
      51,
      53
    ],
    "magicLevel": [
      42,
      49,
      55,
      60,
      64,
      68,
      72
    ],
    "duration": null,
    "skillType": "summon",
    "operateType": "active",
    "target": "self",
    "isMagic": true,
    "ignoreShld": false,
    "weaponsAllowed": [],
    "element": "none",
    "elementPower": 0,
    "levelDepend": 0,
    "ignoreResists": false,
    "canBeReflected": true,
    "effects": []
  },
  {
    "name": "Summon Viper Cubic",
    "id": 278,
    "levels": 6,
    "power": [
      531,
      773,
      1026,
      1264,
      1530,
      1822
    ],
    "mpCost": [
      35,
      40,
      44,
      48,
      51,
      53
    ],
    "magicLevel": [
      49,
      55,
      60,
      64,
      68,
      72
    ],
    "duration": null,
    "skillType": "summon",
    "operateType": "active",
    "target": "self",
    "isMagic": true,
    "ignoreShld": false,
    "weaponsAllowed": [],
    "element": "none",
    "elementPower": 0,
    "levelDepend": 0,
    "ignoreResists": false,
    "canBeReflected": true,
    "effects": []
  },
  {
    "name": "Summon Dark Panther",
    "id": 283,
    "levels": 7,
    "power": [],
    "mpCost": [
      56,
      70,
      85,
      92,
      98,
      104,
      109
    ],
    "magicLevel": [],
    "duration": null,
    "skillType": "summon",
    "operateType": "active",
    "target": "self",
    "isMagic": true,
    "ignoreShld": false,
    "weaponsAllowed": [],
    "element": "none",
    "elementPower": 0,
    "levelDepend": 0,
    "ignoreResists": false,
    "canBeReflected": true,
    "effects": []
  },
  {
    "name": "Summon Wild Hog Cannon",
    "id": 299,
    "levels": 1,
    "power": [],
    "mpCost": [],
    "magicLevel": [],
    "duration": null,
    "skillType": "summon",
    "operateType": "active",
    "target": "self",
    "isMagic": false,
    "ignoreShld": false,
    "weaponsAllowed": [],
    "element": "none",
    "elementPower": 0,
    "levelDepend": 0,
    "ignoreResists": false,
    "canBeReflected": true,
    "effects": []
  },
  {
    "name": "Summon Big Boom",
    "id": 301,
    "levels": 5,
    "power": [],
    "mpCost": [
      74,
      82,
      88,
      94,
      100
    ],
    "magicLevel": [],
    "duration": null,
    "skillType": "summon",
    "operateType": "active",
    "target": "self",
    "isMagic": false,
    "ignoreShld": false,
    "weaponsAllowed": [],
    "element": "none",
    "elementPower": 0,
    "levelDepend": 0,
    "ignoreResists": false,
    "canBeReflected": true,
    "effects": []
  },
  {
    "name": "Summon Swoop Cannon",
    "id": 448,
    "levels": 1,
    "power": [],
    "mpCost": [],
    "magicLevel": [],
    "duration": null,
    "skillType": "summon",
    "operateType": "active",
    "target": "self",
    "isMagic": false,
    "ignoreShld": false,
    "weaponsAllowed": [],
    "element": "none",
    "elementPower": 0,
    "levelDepend": 0,
    "ignoreResists": false,
    "canBeReflected": true,
    "effects": []
  },
  {
    "name": "Summon Attractive Cubic",
    "id": 449,
    "levels": 4,
    "power": [
      1026,
      1264,
      1530,
      1822
    ],
    "mpCost": [
      58,
      62,
      65,
      69
    ],
    "magicLevel": [
      62,
      66,
      70,
      74
    ],
    "duration": null,
    "skillType": "summon",
    "operateType": "active",
    "target": "self",
    "isMagic": true,
    "ignoreShld": false,
    "weaponsAllowed": [],
    "element": "none",
    "elementPower": 0,
    "levelDepend": 0,
    "ignoreResists": false,
    "canBeReflected": true,
    "effects": []
  },
  {
    "name": "Summon Kat the Cat",
    "id": 1111,
    "levels": 18,
    "power": [],
    "mpCost": [
      31,
      35,
      42,
      48,
      56,
      62,
      69,
      75,
      82,
      85,
      88,
      92,
      95,
      98,
      101,
      104,
      106,
      109
    ],
    "magicLevel": [],
    "duration": null,
    "skillType": "summon",
    "operateType": "active",
    "target": "self",
    "isMagic": true,
    "ignoreShld": false,
    "weaponsAllowed": [],
    "element": "none",
    "elementPower": 0,
    "levelDepend": 0,
    "ignoreResists": false,
    "canBeReflected": true,
    "effects": []
  },
  {
    "name": "Summon Shadow",
    "id": 1128,
    "levels": 18,
    "power": [],
    "mpCost": [
      31,
      35,
      42,
      48,
      56,
      62,
      69,
      75,
      82,
      85,
      88,
      92,
      95,
      98,
      101,
      104,
      106,
      109
    ],
    "magicLevel": [],
    "duration": null,
    "skillType": "summon",
    "operateType": "active",
    "target": "self",
    "isMagic": true,
    "ignoreShld": false,
    "weaponsAllowed": [],
    "element": "none",
    "elementPower": 0,
    "levelDepend": 0,
    "ignoreResists": false,
    "canBeReflected": true,
    "effects": []
  },
  {
    "name": "Summon Reanimated Man",
    "id": 1129,
    "levels": 7,
    "power": [],
    "mpCost": [
      62,
      75,
      88,
      95,
      101,
      106,
      109
    ],
    "magicLevel": [],
    "duration": null,
    "skillType": "summon",
    "operateType": "active",
    "target": "corpse_mob",
    "isMagic": true,
    "ignoreShld": false,
    "weaponsAllowed": [],
    "element": "none",
    "elementPower": 0,
    "levelDepend": 0,
    "ignoreResists": false,
    "canBeReflected": true,
    "effects": []
  },
  {
    "name": "Summon Corrupted Man",
    "id": 1154,
    "levels": 6,
    "power": [],
    "mpCost": [
      56,
      69,
      82,
      92,
      98,
      104
    ],
    "magicLevel": [],
    "duration": null,
    "skillType": "summon",
    "operateType": "active",
    "target": "corpse_mob",
    "isMagic": true,
    "ignoreShld": false,
    "weaponsAllowed": [],
    "element": "none",
    "elementPower": 0,
    "levelDepend": 0,
    "ignoreResists": false,
    "canBeReflected": true,
    "effects": []
  },
  {
    "name": "Summon Mew the Cat",
    "id": 1225,
    "levels": 18,
    "power": [],
    "mpCost": [
      31,
      35,
      42,
      48,
      56,
      62,
      69,
      75,
      82,
      85,
      88,
      92,
      95,
      98,
      101,
      104,
      106,
      109
    ],
    "magicLevel": [],
    "duration": null,
    "skillType": "summon",
    "operateType": "active",
    "target": "self",
    "isMagic": true,
    "ignoreShld": false,
    "weaponsAllowed": [],
    "element": "none",
    "elementPower": 0,
    "levelDepend": 0,
    "ignoreResists": false,
    "canBeReflected": true,
    "effects": []
  },
  {
    "name": "Summon Boxer the Unicorn",
    "id": 1226,
    "levels": 18,
    "power": [],
    "mpCost": [
      31,
      35,
      42,
      48,
      56,
      62,
      69,
      75,
      82,
      85,
      88,
      92,
      95,
      98,
      101,
      104,
      106,
      109
    ],
    "magicLevel": [],
    "duration": null,
    "skillType": "summon",
    "operateType": "active",
    "target": "self",
    "isMagic": true,
    "ignoreShld": false,
    "weaponsAllowed": [],
    "element": "none",
    "elementPower": 0,
    "levelDepend": 0,
    "ignoreResists": false,
    "canBeReflected": true,
    "effects": []
  },
  {
    "name": "Summon Mirage the Unicorn",
    "id": 1227,
    "levels": 18,
    "power": [],
    "mpCost": [
      31,
      35,
      42,
      48,
      56,
      62,
      69,
      75,
      82,
      85,
      88,
      92,
      95,
      98,
      101,
      104,
      106,
      109
    ],
    "magicLevel": [],
    "duration": null,
    "skillType": "summon",
    "operateType": "active",
    "target": "self",
    "isMagic": true,
    "ignoreShld": false,
    "weaponsAllowed": [],
    "element": "none",
    "elementPower": 0,
    "levelDepend": 0,
    "ignoreResists": false,
    "canBeReflected": true,
    "effects": []
  },
  {
    "name": "Summon Silhouette",
    "id": 1228,
    "levels": 18,
    "power": [],
    "mpCost": [
      31,
      35,
      42,
      48,
      56,
      62,
      69,
      75,
      82,
      85,
      88,
      92,
      95,
      98,
      101,
      104,
      106,
      109
    ],
    "magicLevel": [],
    "duration": null,
    "skillType": "summon",
    "operateType": "active",
    "target": "self",
    "isMagic": true,
    "ignoreShld": false,
    "weaponsAllowed": [],
    "element": "none",
    "elementPower": 0,
    "levelDepend": 0,
    "ignoreResists": false,
    "canBeReflected": true,
    "effects": []
  },
  {
    "name": "Summon Kai the Cat",
    "id": 1276,
    "levels": 14,
    "power": [],
    "mpCost": [
      56,
      62,
      69,
      75,
      82,
      85,
      88,
      92,
      95,
      98,
      101,
      104,
      106,
      109
    ],
    "magicLevel": [],
    "duration": null,
    "skillType": "summon",
    "operateType": "active",
    "target": "self",
    "isMagic": true,
    "ignoreShld": false,
    "weaponsAllowed": [],
    "element": "none",
    "elementPower": 0,
    "levelDepend": 0,
    "ignoreResists": false,
    "canBeReflected": true,
    "effects": []
  },
  {
    "name": "Summon Merrow the Unicorn",
    "id": 1277,
    "levels": 14,
    "power": [],
    "mpCost": [
      56,
      62,
      69,
      75,
      82,
      85,
      88,
      92,
      95,
      98,
      101,
      104,
      106,
      109
    ],
    "magicLevel": [],
    "duration": null,
    "skillType": "summon",
    "operateType": "active",
    "target": "self",
    "isMagic": true,
    "ignoreShld": false,
    "weaponsAllowed": [],
    "element": "none",
    "elementPower": 0,
    "levelDepend": 0,
    "ignoreResists": false,
    "canBeReflected": true,
    "effects": []
  },
  {
    "name": "Summon Soulless",
    "id": 1278,
    "levels": 14,
    "power": [],
    "mpCost": [
      56,
      62,
      69,
      75,
      82,
      85,
      88,
      92,
      95,
      98,
      101,
      104,
      106,
      109
    ],
    "magicLevel": [],
    "duration": null,
    "skillType": "summon",
    "operateType": "active",
    "target": "self",
    "isMagic": true,
    "ignoreShld": false,
    "weaponsAllowed": [],
    "element": "none",
    "elementPower": 0,
    "levelDepend": 0,
    "ignoreResists": false,
    "canBeReflected": true,
    "effects": []
  },
  {
    "name": "Summon Binding Cubic",
    "id": 1279,
    "levels": 9,
    "power": [
      282,
      377,
      497,
      644,
      820,
      1026,
      1264,
      1530,
      1822
    ],
    "mpCost": [
      28,
      31,
      35,
      38,
      41,
      44,
      48,
      51,
      53
    ],
    "magicLevel": [
      40,
      44,
      48,
      52,
      56,
      60,
      64,
      68,
      72
    ],
    "duration": null,
    "skillType": "summon",
    "operateType": "active",
    "target": "self",
    "isMagic": true,
    "ignoreShld": false,
    "weaponsAllowed": [],
    "element": "none",
    "elementPower": 0,
    "levelDepend": 0,
    "ignoreResists": false,
    "canBeReflected": true,
    "effects": []
  },
  {
    "name": "Summon Aqua Cubic",
    "id": 1280,
    "levels": 9,
    "power": [
      282,
      377,
      497,
      644,
      820,
      1141,
      1394,
      1673,
      1975
    ],
    "mpCost": [
      28,
      31,
      35,
      38,
      41,
      46,
      49,
      52,
      55
    ],
    "magicLevel": [
      40,
      44,
      48,
      52,
      56,
      60,
      64,
      68,
      72
    ],
    "duration": null,
    "skillType": "summon",
    "operateType": "active",
    "target": "self",
    "isMagic": true,
    "ignoreShld": false,
    "weaponsAllowed": [],
    "element": "none",
    "elementPower": 0,
    "levelDepend": 0,
    "ignoreResists": false,
    "canBeReflected": true,
    "effects": []
  },
  {
    "name": "Summon Spark Cubic",
    "id": 1281,
    "levels": 9,
    "power": [
      282,
      377,
      497,
      644,
      820,
      1026,
      1264,
      1530,
      1822
    ],
    "mpCost": [
      28,
      31,
      35,
      38,
      41,
      44,
      48,
      51,
      53
    ],
    "magicLevel": [
      40,
      44,
      48,
      52,
      56,
      60,
      64,
      68,
      72
    ],
    "duration": null,
    "skillType": "summon",
    "operateType": "active",
    "target": "self",
    "isMagic": true,
    "ignoreShld": false,
    "weaponsAllowed": [],
    "element": "none",
    "elementPower": 0,
    "levelDepend": 0,
    "ignoreResists": false,
    "canBeReflected": true,
    "effects": []
  },
  {
    "name": "Mass Summon Storm Cubic",
    "id": 1328,
    "levels": 8,
    "power": [
      282,
      434,
      677,
      919,
      1141,
      1394,
      1673,
      1975
    ],
    "mpCost": [
      111,
      130,
      150,
      170,
      183,
      195,
      207,
      217
    ],
    "magicLevel": [
      40,
      46,
      52,
      58,
      62,
      66,
      70,
      74
    ],
    "duration": null,
    "skillType": "summon",
    "operateType": "active",
    "target": "party",
    "isMagic": true,
    "ignoreShld": false,
    "weaponsAllowed": [],
    "element": "none",
    "elementPower": 0,
    "levelDepend": 0,
    "ignoreResists": false,
    "canBeReflected": true,
    "effects": []
  },
  {
    "name": "Mass Summon Aqua Cubic",
    "id": 1329,
    "levels": 9,
    "power": [
      282,
      377,
      497,
      644,
      820,
      1141,
      1394,
      1673,
      1975
    ],
    "mpCost": [
      111,
      123,
      137,
      150,
      163,
      183,
      195,
      207,
      217
    ],
    "magicLevel": [
      40,
      44,
      48,
      52,
      56,
      60,
      64,
      68,
      72
    ],
    "duration": null,
    "skillType": "summon",
    "operateType": "active",
    "target": "party",
    "isMagic": true,
    "ignoreShld": false,
    "weaponsAllowed": [],
    "element": "none",
    "elementPower": 0,
    "levelDepend": 0,
    "ignoreResists": false,
    "canBeReflected": true,
    "effects": []
  },
  {
    "name": "Mass Summon Phantom Cubic",
    "id": 1330,
    "levels": 8,
    "power": [
      282,
      434,
      644,
      919,
      1141,
      1394,
      1673,
      1975
    ],
    "mpCost": [
      111,
      130,
      150,
      170,
      183,
      195,
      207,
      217
    ],
    "magicLevel": [
      40,
      46,
      52,
      58,
      62,
      66,
      70,
      74
    ],
    "duration": null,
    "skillType": "summon",
    "operateType": "active",
    "target": "party",
    "isMagic": true,
    "ignoreShld": false,
    "weaponsAllowed": [],
    "element": "none",
    "elementPower": 0,
    "levelDepend": 0,
    "ignoreResists": false,
    "canBeReflected": true,
    "effects": []
  },
  {
    "name": "Summon Feline Queen",
    "id": 1331,
    "levels": 10,
    "power": [],
    "mpCost": [
      56,
      92,
      69,
      75,
      82,
      85,
      88,
      92,
      95,
      98
    ],
    "magicLevel": [],
    "duration": null,
    "skillType": "summon",
    "operateType": "active",
    "target": "self",
    "isMagic": true,
    "ignoreShld": false,
    "weaponsAllowed": [],
    "element": "none",
    "elementPower": 0,
    "levelDepend": 0,
    "ignoreResists": false,
    "canBeReflected": true,
    "effects": []
  },
  {
    "name": "Summon Unicorn Seraphim",
    "id": 1332,
    "levels": 10,
    "power": [],
    "mpCost": [
      56,
      92,
      69,
      75,
      82,
      85,
      88,
      92,
      95,
      98
    ],
    "magicLevel": [],
    "duration": null,
    "skillType": "summon",
    "operateType": "active",
    "target": "self",
    "isMagic": true,
    "ignoreShld": false,
    "weaponsAllowed": [],
    "element": "none",
    "elementPower": 0,
    "levelDepend": 0,
    "ignoreResists": false,
    "canBeReflected": true,
    "effects": []
  },
  {
    "name": "Summon Nightshade",
    "id": 1333,
    "levels": 10,
    "power": [],
    "mpCost": [
      56,
      92,
      69,
      75,
      82,
      85,
      88,
      92,
      95,
      98
    ],
    "magicLevel": [],
    "duration": null,
    "skillType": "summon",
    "operateType": "active",
    "target": "self",
    "isMagic": true,
    "ignoreShld": false,
    "weaponsAllowed": [],
    "element": "none",
    "elementPower": 0,
    "levelDepend": 0,
    "ignoreResists": false,
    "canBeReflected": true,
    "effects": []
  },
  {
    "name": "Summon Cursed Man",
    "id": 1334,
    "levels": 7,
    "power": [],
    "mpCost": [
      82,
      88,
      95,
      101,
      104,
      106,
      109
    ],
    "magicLevel": [],
    "duration": null,
    "skillType": "summon",
    "operateType": "active",
    "target": "corpse_mob",
    "isMagic": true,
    "ignoreShld": false,
    "weaponsAllowed": [],
    "element": "none",
    "elementPower": 0,
    "levelDepend": 0,
    "ignoreResists": false,
    "canBeReflected": true,
    "effects": []
  },
  {
    "name": "Summon Feline King",
    "id": 1406,
    "levels": 1,
    "power": [],
    "mpCost": [
      116
    ],
    "magicLevel": [],
    "duration": null,
    "skillType": "summon",
    "operateType": "active",
    "target": "self",
    "isMagic": true,
    "ignoreShld": false,
    "weaponsAllowed": [],
    "element": "none",
    "elementPower": 0,
    "levelDepend": 0,
    "ignoreResists": false,
    "canBeReflected": true,
    "effects": []
  },
  {
    "name": "Summon Magnus the Unicorn",
    "id": 1407,
    "levels": 1,
    "power": [],
    "mpCost": [
      116
    ],
    "magicLevel": [],
    "duration": null,
    "skillType": "summon",
    "operateType": "active",
    "target": "self",
    "isMagic": true,
    "ignoreShld": false,
    "weaponsAllowed": [],
    "element": "none",
    "elementPower": 0,
    "levelDepend": 0,
    "ignoreResists": false,
    "canBeReflected": true,
    "effects": []
  },
  {
    "name": "Summon Spectral Lord",
    "id": 1408,
    "levels": 1,
    "power": [],
    "mpCost": [
      116
    ],
    "magicLevel": [],
    "duration": null,
    "skillType": "summon",
    "operateType": "active",
    "target": "self",
    "isMagic": true,
    "ignoreShld": false,
    "weaponsAllowed": [],
    "element": "none",
    "elementPower": 0,
    "levelDepend": 0,
    "ignoreResists": false,
    "canBeReflected": true,
    "effects": []
  },
  {
    "name": "Life Cubic for Beginners",
    "id": 4338,
    "levels": 1,
    "power": [],
    "mpCost": [],
    "magicLevel": [
      18
    ],
    "duration": null,
    "skillType": "summon",
    "operateType": "active",
    "target": "self",
    "isMagic": true,
    "ignoreShld": false,
    "weaponsAllowed": [],
    "element": "none",
    "elementPower": 0,
    "levelDepend": 0,
    "ignoreResists": false,
    "canBeReflected": true,
    "effects": []
  },
  {
    "name": "Summon King Bugbear",
    "id": 7030,
    "levels": 1,
    "power": [],
    "mpCost": [
      3
    ],
    "magicLevel": [],
    "duration": null,
    "skillType": "summon",
    "operateType": "active",
    "target": "self",
    "isMagic": true,
    "ignoreShld": false,
    "weaponsAllowed": [],
    "element": "none",
    "elementPower": 0,
    "levelDepend": 0,
    "ignoreResists": false,
    "canBeReflected": true,
    "effects": []
  },
  {
    "name": "Summon Skeleton Royal Guard",
    "id": 7031,
    "levels": 1,
    "power": [],
    "mpCost": [
      3
    ],
    "magicLevel": [],
    "duration": null,
    "skillType": "summon",
    "operateType": "active",
    "target": "self",
    "isMagic": true,
    "ignoreShld": false,
    "weaponsAllowed": [],
    "element": "none",
    "elementPower": 0,
    "levelDepend": 0,
    "ignoreResists": false,
    "canBeReflected": true,
    "effects": []
  },
  {
    "name": "Summon Hunter Gargoyle",
    "id": 7032,
    "levels": 1,
    "power": [],
    "mpCost": [
      3
    ],
    "magicLevel": [],
    "duration": null,
    "skillType": "summon",
    "operateType": "active",
    "target": "self",
    "isMagic": true,
    "ignoreShld": false,
    "weaponsAllowed": [],
    "element": "none",
    "elementPower": 0,
    "levelDepend": 0,
    "ignoreResists": false,
    "canBeReflected": true,
    "effects": []
  }
]